[
  {
    "name": "Processor",
    "imgsrc": "images/processor.png",
    "specs": [
      {
        "title": "AMD 3990X",
        "price": 3749.00
      },
      {
        "title": "Intel W-3175X",
        "price": 3321.00
      },
      {
        "title": "AMD 3970X",
        "price": 1899.00
      },
      {
        "title": "Intel 10980XE",
        "price": 1099.00
      },
      {
        "title": "AMD 3900x",
        "price": 489.00
      }
    ]
  },
  {
    "name": "RAM",
    "imgsrc": "images/ram.png",
    "specs": [
      {
        "title": "256GB",
        "price": 1108.00
      },
      {
        "title": "128GB",
        "price": 748.00
      },
      {
        "title": "64GB",
        "price": 329.00
      },
      {
        "title": "32GB",
        "price": 139.00
      }
    ]
  },
  {
    "name": "NVMe-SSD",
    "imgsrc": "images/ssd.png",
    "specs": [
      {
        "title": "4TB",
        "price": 849.00
      },
      {
        "title": "2TB",
        "price": 699.00
      },
      {
        "title": "1TB",
        "price": 149.00
      }
    ]
  },
  {
    "name": "HDD",
    "imgsrc": "images/hard disk.png",
    "specs": [
      {
        "title": "16TB",
        "price": 501.00
      },
      {
        "title": "12TB",
        "price": 329.00
      },
      {
        "title": "8TB",
        "price": 152.00
      },
      {
        "title": "4TB",
        "price": 92.00
      }
    ]
  },
  {
    "name": "Graphics-Card",
    "imgsrc": "images/graphics card.png",
    "specs": [
      {
        "title": "Nvidia Quadro RTX 8000",
        "price": 5545.00
      },
      {
        "title": "Nvidia Titan RTX",
        "price": 2489.00
      },
      {
        "title": "Nvidia RTX 2080TI",
        "price": 1289.00
      }
    ]
  }
]
